{
  "slug": "agcsoft-sia-produkta-vaditajs-cpo-chief-product-officer-1616007",
  "title": "Produkta vadītājs (CPO) — Chief Product Officer",
  "company": "AGCSOFT SIA",
  "companyUrl": "https://cv.lv/lv/search/employer/agcsoft-sia?employerId=66129",
  "location": "Hanzas 2A",
  "remote": "onsite",
  "employment": "full-time",
  "seniority": "staff",
  "stack": [],
  "summary": {
    "lv": "AGCSOFT SIA meklē Chief Product Officer (CPO), kurš vadīs uzņēmuma produktu stratēģiju un komandu IT risinājumu izstrādē. Atalgojums €7230 mēnesī.",
    "en": "AGCSOFT SIA is seeking a Chief Product Officer (CPO) to lead the company's product strategy and team in the IT solutions development space, offering €7,230/month."
  },
  "applyUrl": "https://cv.lv/vacancy/1616007/agcsoft-sia/produkta-vaditajs-cpo-chief-product-officer",
  "postedAt": "2026-07-13",
  "salaryRange": "€7230",
  "expiresAt": "2026-08-13"
}