{
  "slug": "bilderlings-data-analyst",
  "title": "Data Analyst",
  "company": "Bilderlings Pay SIA",
  "companyUrl": "http://www.bilderlings.com",
  "location": "Rīga",
  "remote": "onsite",
  "employment": "full-time",
  "seniority": "mid",
  "salaryRange": "€2500–3700",
  "stack": ["sql"],
  "summary": {
    "lv": "Bilderlings, Lielbritānijas Fintech tirgus līderis ar SEPA un SWIFT maksājumiem, meklē datu analītiķi pievienoties komandai birojā Vecrīgā.",
    "en": "Bilderlings, a UK Fintech leader offering fast SEPA and international SWIFT payments, is hiring a Data Analyst for its Old Riga office team."
  },
  "applyUrl": "https://cv.lv/vacancy/1580341/bilderlings-pay-sia/data-analyst",
  "postedAt": "2026-05-26"
}
