{
  "slug": "entain-nce-sportsbook-analytics-manager",
  "title": "Sportsbook Analytics Manager",
  "company": "Entain NCE",
  "companyUrl": "https://entaingroup.com/",
  "location": "Rīga",
  "remote": "hybrid",
  "employment": "full-time",
  "seniority": "senior",
  "salaryRange": "€3000+",
  "stack": [
    "sql",
    "python",
    "data-analysis",
    "bi"
  ],
  "summary": {
    "lv": "Entain meklē Sportsbook Analytics Manager, kas attīstīs uz datiem balstītu kultūru sporta likmju komandā — datu analīze, ieskatu izstrāde un produkta lēmumu informēšana straujā vidē.",
    "en": "Entain is hiring a Sportsbook Analytics Manager to drive a data-led culture in the sports betting team — running analysis, surfacing insights and informing product decisions in a fast-paced environment."
  },
  "applyUrl": "https://cv.lv/vacancy/1583331/entain-nce/sportsbook-analytics-manager",
  "postedAt": "2026-05-22",
  "expiresAt": "2026-06-22"
}
