{
  "slug": "intrum-global-technologies-data-governance-specialist",
  "title": "Data Governance Specialist",
  "company": "Intrum Global Technologies",
  "companyUrl": "https://cv.lv/lv/search/employer/intrum-global-technologies?employerId=30911",
  "location": "Ieriķu iela 5, Rīga",
  "remote": "hybrid",
  "employment": "full-time",
  "seniority": "mid",
  "stack": [
    "data-governance"
  ],
  "summary": {
    "lv": "Intrum Global Technologies meklē datu pārvaldības speciālistu uzņēmuma datu pārvaldības standartu ieviešanai un risku mazināšanai.",
    "en": "Intrum Global Technologies is seeking a Data Governance Specialist to implement enterprise data governance standards and mitigate data risks."
  },
  "applyUrl": "https://cv.lv/vacancy/1608206/intrum-global-technologies/data-governance-specialist",
  "postedAt": "2026-06-30",
  "salaryRange": "€3500–4500/mēn",
  "expiresAt": "2026-07-30"
}
