{
  "slug": "sia-novikontas-juras-koledza-junior-training-content-developer",
  "title": "Junior Training Content Developer",
  "company": "SIA Novikontas Jūras koledža",
  "companyUrl": "https://cv.lv/lv/search/employer/sia-novikontas-juras-koledza?employerId=28329",
  "location": "Rīga",
  "remote": "onsite",
  "employment": "full-time",
  "seniority": "junior",
  "salaryRange": "€1500",
  "stack": [
    "ai"
  ],
  "summary": {
    "lv": "Jaunākais apmācību satura izstrādātājs Novikontas Academy (jūrnieku mācības), kas pārvērš ekspertu zināšanas apgūstamā mācību saturā no idejas līdz gatavam produktam, izmantojot mākslīgā intelekta rīkus. Nepieciešama vismaz vidējā izglītība un brīva angļu valoda; nozares pieredze nav nepieciešama.",
    "en": "Junior Training Content Developer at Novikontas Academy (maritime training) turning expert knowledge into learnable course content end-to-end, using AI tools to do the heavy lifting. Secondary education or above and fluent English; no industry background needed."
  },
  "applyUrl": "https://cv.lv/vacancy/1591070/sia-novikontas-juras-koledza/junior-training-content-developer",
  "postedAt": "2026-06-02",
  "expiresAt": "2026-06-25"
}
