{
  "slug": "ubiquiti-latvia-sia-ai-driven-qa-engineer",
  "title": "AI-driven QA Engineer",
  "company": "Ubiquiti (Latvia) SIA",
  "companyUrl": "https://cv.lv/lv/search/employer/ubiquiti-latvia-sia?employerId=30898",
  "location": "Rīga",
  "remote": "hybrid",
  "employment": "full-time",
  "seniority": "mid",
  "stack": [
    "qa",
    "ai",
    "test-automation",
    "python"
  ],
  "summary": {
    "lv": "Ubiquiti Latvia meklē AI-driven QA inženieri/-i, kurš/-a izmantošot AI rīkus testēšanas procesu automatizācijai un uzlabošanai.",
    "en": "Ubiquiti Latvia is looking for an AI-driven QA Engineer to leverage AI tools for automating and improving testing processes for their networking and smart home products."
  },
  "applyUrl": "https://cv.lv/vacancy/1623122/ubiquiti-latvia-sia/ai-driven-qa-engineer",
  "postedAt": "2026-07-21",
  "salaryRange": "€2500–5000",
  "expiresAt": "2026-08-21"
}