{
  "slug": "yo-hr-consultancy-data-scientist",
  "title": "Data Scientist",
  "company": "YO HR Consultancy",
  "companyUrl": "https://remoteok.com/yo-hr-consultancy",
  "location": "Remote · Anywhere",
  "remote": "remote",
  "employment": "contract",
  "seniority": "mid",
  "stack": [],
  "summary": {
    "lv": "Attālināta līgumdarba Data Scientist (datu zinātnieka) pozīcija, ko reklamē personāla atlases aģentūra. Sludinājums ir īss un norāda uz LinkedIn pilnam amata aprakstam.",
    "en": "A remote contract Data Scientist position advertised through a recruiting agency. The listing is brief and links to LinkedIn for the full job description."
  },
  "applyUrl": "https://remoteok.com/remote-jobs/remote-data-scientist-yo-hr-consultancy-1133043",
  "postedAt": "2026-06-09",
  "expiresAt": "2026-09-07"
}
