{
  "slug": "2026-07-02-applied-ai-focused-155th-devclub-lv",
  "title": {
    "en": "Applied AI focused 155th DevClub.lv",
    "lv": "Applied AI focused 155th DevClub.lv"
  },
  "date": "2026-07-02",
  "location": "Rīga",
  "venue": "GoCardless, Novira Plaza, 3rd floor",
  "url": "https://www.eventbrite.com/e/applied-ai-focused-155th-devclublv-registration-1992560972507",
  "organizer": "DevClub.lv",
  "kind": "meetup",
  "techTags": ["ai", "developer-tools", "software-engineering", "code-review"],
  "audienceTags": ["engineers", "developers"],
  "summary": {
    "en": "The 155th DevClub.lv meetup focusing on practical AI for developers: AI-assisted code review, deterministic workflows, and secure access to private company knowledge, hosted at GoCardless Riga office.",
    "lv": "155. DevClub.lv tikšanās par praktisko AI izstrādātājiem: AI palīdzēta koda pārskatīšana, deterministiski darbplūsmu risinājumi un droša piekļuve uzņēmuma privātajām zināšanu bāzēm, GoCardless Rīgas birojā."
  },
  "image": "https://cdn.evbuc.com/images/1187630185/33330097863/1/original.20260625-110946"
}
